bobby/__about__.py
bobby/__init__.py
bobby-0.0.1.dist-info/METADATA
bobby-0.0.1.dist-info/WHEEL
bobby-0.0.1.dist-info/licenses/LICENSE.txt
bobby-0.0.1.dist-info/RECORD
