Metadata-Version: 2.4
Name: bobby
Version: 0.0.1
Summary: Namespace Package for [Bobby Pills](https://www.bobbypills.com/) Animation Studio.
Project-URL: Documentation, https://github.com/dee909/bobby#readme
Project-URL: Issues, https://github.com/dee909/bobby/issues
Project-URL: Source, https://github.com/dee909/bobby
Author-email: dee909 <dee909@gmail.com>
License-Expression: MIT
License-File: LICENSE.txt
Classifier: Development Status :: 4 - Beta
Classifier: Programming Language :: Python
Classifier: Programming Language :: Python :: 3.8
Classifier: Programming Language :: Python :: 3.9
Classifier: Programming Language :: Python :: 3.10
Classifier: Programming Language :: Python :: 3.11
Classifier: Programming Language :: Python :: 3.12
Classifier: Programming Language :: Python :: Implementation :: CPython
Classifier: Programming Language :: Python :: Implementation :: PyPy
Requires-Python: >=3.8
